{
  "openapi": "3.0.1",
  "info": {
    "title": "ColdDream.Api",
    "version": "1.0"
  },
  "paths": {
    "/api/Auth/register": {
      "post": {
        "tags": [
          "Auth"
        ],
        "requestBody": {
          "content": {
            "application/json": {
              "schema": {
                "$ref": "#/components/schemas/RegisterDto"
              }
            },
            "text/json": {
              "schema": {
                "$ref": "#/components/schemas/RegisterDto"
              }
            },
            "application/*+json": {
              "schema": {
                "$ref": "#/components/schemas/RegisterDto"
              }
            }
          }
        },
        "responses": {
          "200": {
            "description": "Success"
          }
        }
      }
    },
    "/api/Auth/login": {
      "post": {
        "tags": [
          "Auth"
        ],
        "requestBody": {
          "content": {
            "application/json": {
              "schema": {
                "$ref": "#/components/schemas/LoginDto"
              }
            },
            "text/json": {
              "schema": {
                "$ref": "#/components/schemas/LoginDto"
              }
            },
            "application/*+json": {
              "schema": {
                "$ref": "#/components/schemas/LoginDto"
              }
            }
          }
        },
        "responses": {
          "200": {
            "description": "Success"
          }
        }
      }
    },
    "/api/Bookings": {
      "post": {
        "tags": [
          "Bookings"
        ],
        "requestBody": {
          "content": {
            "application/json": {
              "schema": {
                "$ref": "#/components/schemas/Booking"
              }
            },
            "text/json": {
              "schema": {
                "$ref": "#/components/schemas/Booking"
              }
            },
            "application/*+json": {
              "schema": {
                "$ref": "#/components/schemas/Booking"
              }
            }
          }
        },
        "responses": {
          "200": {
            "description": "Success"
          }
        }
      }
    },
    "/api/Bookings/{id}": {
      "get": {
        "tags": [
          "Bookings"
        ],
        "parameters": [
          {
            "name": "id",
            "in": "path",
            "required": true,
            "schema": {
              "type": "string",
              "format": "uuid"
            }
          }
        ],
        "responses": {
          "200": {
            "description": "Success"
          }
        }
      },
      "put": {
        "tags": [
          "Bookings"
        ],
        "parameters": [
          {
            "name": "id",
            "in": "path",
            "required": true,
            "schema": {
              "type": "string",
              "format": "uuid"
            }
          }
        ],
        "requestBody": {
          "content": {
            "application/json": {
              "schema": {
                "$ref": "#/components/schemas/Booking"
              }
            },
            "text/json": {
              "schema": {
                "$ref": "#/components/schemas/Booking"
              }
            },
            "application/*+json": {
              "schema": {
                "$ref": "#/components/schemas/Booking"
              }
            }
          }
        },
        "responses": {
          "200": {
            "description": "Success"
          }
        }
      }
    },
    "/api/Bookings/my": {
      "get": {
        "tags": [
          "Bookings"
        ],
        "responses": {
          "200": {
            "description": "Success"
          }
        }
      }
    },
    "/api/Bookings/{id}/cancel": {
      "post": {
        "tags": [
          "Bookings"
        ],
        "parameters": [
          {
            "name": "id",
            "in": "path",
            "required": true,
            "schema": {
              "type": "string",
              "format": "uuid"
            }
          }
        ],
        "responses": {
          "200": {
            "description": "Success"
          }
        }
      }
    },
    "/api/Butlers": {
      "get": {
        "tags": [
          "Butlers"
        ],
        "responses": {
          "200": {
            "description": "Success"
          }
        }
      },
      "post": {
        "tags": [
          "Butlers"
        ],
        "requestBody": {
          "content": {
            "application/json": {
              "schema": {
                "$ref": "#/components/schemas/Butler"
              }
            },
            "text/json": {
              "schema": {
                "$ref": "#/components/schemas/Butler"
              }
            },
            "application/*+json": {
              "schema": {
                "$ref": "#/components/schemas/Butler"
              }
            }
          }
        },
        "responses": {
          "200": {
            "description": "Success"
          }
        }
      }
    },
    "/api/Butlers/{id}": {
      "get": {
        "tags": [
          "Butlers"
        ],
        "parameters": [
          {
            "name": "id",
            "in": "path",
            "required": true,
            "schema": {
              "type": "string",
              "format": "uuid"
            }
          }
        ],
        "responses": {
          "200": {
            "description": "Success"
          }
        }
      },
      "put": {
        "tags": [
          "Butlers"
        ],
        "parameters": [
          {
            "name": "id",
            "in": "path",
            "required": true,
            "schema": {
              "type": "string",
              "format": "uuid"
            }
          }
        ],
        "requestBody": {
          "content": {
            "application/json": {
              "schema": {
                "$ref": "#/components/schemas/Butler"
              }
            },
            "text/json": {
              "schema": {
                "$ref": "#/components/schemas/Butler"
              }
            },
            "application/*+json": {
              "schema": {
                "$ref": "#/components/schemas/Butler"
              }
            }
          }
        },
        "responses": {
          "200": {
            "description": "Success"
          }
        }
      },
      "delete": {
        "tags": [
          "Butlers"
        ],
        "parameters": [
          {
            "name": "id",
            "in": "path",
            "required": true,
            "schema": {
              "type": "string",
              "format": "uuid"
            }
          }
        ],
        "responses": {
          "200": {
            "description": "Success"
          }
        }
      }
    },
    "/api/Butlers/route/{routeId}": {
      "get": {
        "tags": [
          "Butlers"
        ],
        "parameters": [
          {
            "name": "routeId",
            "in": "path",
            "required": true,
            "schema": {
              "type": "string",
              "format": "uuid"
            }
          }
        ],
        "responses": {
          "200": {
            "description": "Success"
          }
        }
      }
    },
    "/api/Butlers/{butlerId}/assign/{routeId}": {
      "post": {
        "tags": [
          "Butlers"
        ],
        "parameters": [
          {
            "name": "butlerId",
            "in": "path",
            "required": true,
            "schema": {
              "type": "string",
              "format": "uuid"
            }
          },
          {
            "name": "routeId",
            "in": "path",
            "required": true,
            "schema": {
              "type": "string",
              "format": "uuid"
            }
          }
        ],
        "responses": {
          "200": {
            "description": "Success"
          }
        }
      }
    },
    "/api/Leaderboard/top-routes": {
      "get": {
        "tags": [
          "Leaderboard"
        ],
        "parameters": [
          {
            "name": "count",
            "in": "query",
            "schema": {
              "type": "integer",
              "format": "int32",
              "default": 10
            }
          }
        ],
        "responses": {
          "200": {
            "description": "Success"
          }
        }
      }
    },
    "/api/Leaderboard/click/{routeId}": {
      "post": {
        "tags": [
          "Leaderboard"
        ],
        "parameters": [
          {
            "name": "routeId",
            "in": "path",
            "required": true,
            "schema": {
              "type": "string",
              "format": "uuid"
            }
          }
        ],
        "responses": {
          "200": {
            "description": "Success"
          }
        }
      }
    },
    "/api/Products": {
      "get": {
        "tags": [
          "Products"
        ],
        "responses": {
          "200": {
            "description": "Success"
          }
        }
      },
      "post": {
        "tags": [
          "Products"
        ],
        "requestBody": {
          "content": {
            "application/json": {
              "schema": {
                "$ref": "#/components/schemas/Product"
              }
            },
            "text/json": {
              "schema": {
                "$ref": "#/components/schemas/Product"
              }
            },
            "application/*+json": {
              "schema": {
                "$ref": "#/components/schemas/Product"
              }
            }
          }
        },
        "responses": {
          "200": {
            "description": "Success"
          }
        }
      }
    },
    "/api/Products/{id}": {
      "get": {
        "tags": [
          "Products"
        ],
        "parameters": [
          {
            "name": "id",
            "in": "path",
            "required": true,
            "schema": {
              "type": "string",
              "format": "uuid"
            }
          }
        ],
        "responses": {
          "200": {
            "description": "Success"
          }
        }
      }
    },
    "/api/Products/{id}/buy": {
      "post": {
        "tags": [
          "Products"
        ],
        "parameters": [
          {
            "name": "id",
            "in": "path",
            "required": true,
            "schema": {
              "type": "string",
              "format": "uuid"
            }
          }
        ],
        "responses": {
          "200": {
            "description": "Success"
          }
        }
      }
    },
    "/api/TourRoutes": {
      "get": {
        "tags": [
          "TourRoutes"
        ],
        "responses": {
          "200": {
            "description": "Success"
          }
        }
      },
      "post": {
        "tags": [
          "TourRoutes"
        ],
        "requestBody": {
          "content": {
            "application/json": {
              "schema": {
                "$ref": "#/components/schemas/TourRoute"
              }
            },
            "text/json": {
              "schema": {
                "$ref": "#/components/schemas/TourRoute"
              }
            },
            "application/*+json": {
              "schema": {
                "$ref": "#/components/schemas/TourRoute"
              }
            }
          }
        },
        "responses": {
          "200": {
            "description": "Success"
          }
        }
      }
    },
    "/api/TourRoutes/{id}": {
      "get": {
        "tags": [
          "TourRoutes"
        ],
        "parameters": [
          {
            "name": "id",
            "in": "path",
            "required": true,
            "schema": {
              "type": "string",
              "format": "uuid"
            }
          }
        ],
        "responses": {
          "200": {
            "description": "Success"
          }
        }
      }
    }
  },
  "components": {
    "schemas": {
      "Booking": {
        "required": [
          "orderNumber"
        ],
        "type": "object",
        "properties": {
          "id": {
            "type": "string",
            "format": "uuid"
          },
          "userId": {
            "type": "string",
            "format": "uuid"
          },
          "user": {
            "$ref": "#/components/schemas/User"
          },
          "tourRouteId": {
            "type": "string",
            "format": "uuid"
          },
          "tourRoute": {
            "$ref": "#/components/schemas/TourRoute"
          },
          "butlerId": {
            "type": "string",
            "format": "uuid",
            "nullable": true
          },
          "butler": {
            "$ref": "#/components/schemas/Butler"
          },
          "status": {
            "type": "string",
            "nullable": true
          },
          "orderNumber": {
            "minLength": 1,
            "type": "string"
          },
          "peopleCount": {
            "type": "integer",
            "format": "int32"
          },
          "timeSlot": {
            "$ref": "#/components/schemas/TimeSlot"
          },
          "contactName": {
            "type": "string",
            "nullable": true
          },
          "contactPhone": {
            "type": "string",
            "nullable": true
          },
          "totalAmount": {
            "type": "number",
            "format": "double"
          },
          "travelDate": {
            "type": "string",
            "format": "date-time"
          },
          "createdAt": {
            "type": "string",
            "format": "date-time"
          }
        },
        "additionalProperties": false
      },
      "Butler": {
        "required": [
          "name"
        ],
        "type": "object",
        "properties": {
          "id": {
            "type": "string",
            "format": "uuid"
          },
          "name": {
            "minLength": 1,
            "type": "string"
          },
          "avatarUrl": {
            "type": "string",
            "nullable": true
          },
          "price": {
            "type": "number",
            "format": "double"
          },
          "tags": {
            "type": "string",
            "nullable": true
          },
          "rating": {
            "type": "number",
            "format": "double"
          },
          "tourRoutes": {
            "type": "array",
            "items": {
              "$ref": "#/components/schemas/TourRoute"
            },
            "nullable": true
          },
          "createdAt": {
            "type": "string",
            "format": "date-time"
          }
        },
        "additionalProperties": false
      },
      "LoginDto": {
        "required": [
          "password",
          "username"
        ],
        "type": "object",
        "properties": {
          "username": {
            "minLength": 1,
            "type": "string"
          },
          "password": {
            "minLength": 1,
            "type": "string"
          }
        },
        "additionalProperties": false
      },
      "Product": {
        "required": [
          "name"
        ],
        "type": "object",
        "properties": {
          "id": {
            "type": "string",
            "format": "uuid"
          },
          "name": {
            "minLength": 1,
            "type": "string"
          },
          "description": {
            "type": "string",
            "nullable": true
          },
          "imageUrl": {
            "type": "string",
            "nullable": true
          },
          "pointsPrice": {
            "type": "integer",
            "format": "int32"
          },
          "stock": {
            "type": "integer",
            "format": "int32"
          },
          "createdAt": {
            "type": "string",
            "format": "date-time"
          }
        },
        "additionalProperties": false
      },
      "RegisterDto": {
        "required": [
          "email",
          "password",
          "username"
        ],
        "type": "object",
        "properties": {
          "username": {
            "minLength": 1,
            "type": "string"
          },
          "email": {
            "minLength": 1,
            "type": "string",
            "format": "email"
          },
          "password": {
            "minLength": 1,
            "type": "string"
          },
          "nickName": {
            "type": "string",
            "nullable": true
          }
        },
        "additionalProperties": false
      },
      "TimeSlot": {
        "enum": [
          0,
          1
        ],
        "type": "integer",
        "format": "int32"
      },
      "TourRoute": {
        "required": [
          "title"
        ],
        "type": "object",
        "properties": {
          "id": {
            "type": "string",
            "format": "uuid"
          },
          "title": {
            "minLength": 1,
            "type": "string"
          },
          "description": {
            "type": "string",
            "nullable": true
          },
          "isPrivate": {
            "type": "boolean"
          },
          "price": {
            "type": "number",
            "format": "double"
          },
          "tags": {
            "type": "string",
            "nullable": true
          },
          "imageUrl": {
            "type": "string",
            "nullable": true
          },
          "butlers": {
            "type": "array",
            "items": {
              "$ref": "#/components/schemas/Butler"
            },
            "nullable": true
          },
          "createdAt": {
            "type": "string",
            "format": "date-time"
          }
        },
        "additionalProperties": false
      },
      "User": {
        "type": "object",
        "properties": {
          "id": {
            "type": "string",
            "format": "uuid"
          },
          "userName": {
            "type": "string",
            "nullable": true
          },
          "normalizedUserName": {
            "type": "string",
            "nullable": true
          },
          "email": {
            "type": "string",
            "nullable": true
          },
          "normalizedEmail": {
            "type": "string",
            "nullable": true
          },
          "emailConfirmed": {
            "type": "boolean"
          },
          "passwordHash": {
            "type": "string",
            "nullable": true
          },
          "securityStamp": {
            "type": "string",
            "nullable": true
          },
          "concurrencyStamp": {
            "type": "string",
            "nullable": true
          },
          "phoneNumber": {
            "type": "string",
            "nullable": true
          },
          "phoneNumberConfirmed": {
            "type": "boolean"
          },
          "twoFactorEnabled": {
            "type": "boolean"
          },
          "lockoutEnd": {
            "type": "string",
            "format": "date-time",
            "nullable": true
          },
          "lockoutEnabled": {
            "type": "boolean"
          },
          "accessFailedCount": {
            "type": "integer",
            "format": "int32"
          },
          "openId": {
            "type": "string",
            "nullable": true
          },
          "nickName": {
            "type": "string",
            "nullable": true
          },
          "points": {
            "type": "integer",
            "format": "int32"
          },
          "createdAt": {
            "type": "string",
            "format": "date-time"
          }
        },
        "additionalProperties": false
      }
    }
  }
}